buildout.cfg
setup.py
docs/HISTORY.txt
etc/README.txt
inc/paste.ini.in
src/README.txt
src/mr/__init__.py
src/mr.monster.egg-info/PKG-INFO
src/mr.monster.egg-info/SOURCES.txt
src/mr.monster.egg-info/dependency_links.txt
src/mr.monster.egg-info/entry_points.txt
src/mr.monster.egg-info/namespace_packages.txt
src/mr.monster.egg-info/not-zip-safe
src/mr.monster.egg-info/requires.txt
src/mr.monster.egg-info/top_level.txt
src/mr/monster/README.txt
src/mr/monster/__init__.py
src/mr/monster/drop.py
src/mr/monster/rewrite.py
src/mr/monster/tests/__init__.py
src/mr/monster/tests/test_eledrop.py
src/mr/monster/tests/test_url.py