Metadata-Version: 1.0
Name: mr.monster
Version: 1.4
Summary: A URL rewriting middleware that emulates a VHM url.
Home-page: http://www.teamrubber.com
Author: Matthew Wilkes
Author-email: matt.wilkes@teamrubber.com
License: BSD
Platform: UNKNOWN
Classifier: Programming Language :: Python
Classifier: Topic :: Software Development :: Libraries :: Python Modules
